pykeybasebot/__init__.py
pykeybasebot/bot.py
pykeybasebot/chat_client.py
pykeybasebot/cli.py
pykeybasebot/errors.py
pykeybasebot/kbevent.py
pykeybasebot/kvstore_client.py
pykeybasebot/types/__init__.py
pykeybasebot/types/chat1/__init__.py
pykeybasebot/types/gregor1/__init__.py
pykeybasebot/types/keybase1/__init__.py
pykeybasebot/types/stellar1/__init__.py
pykeybasebot-0.2.1.dist-info/LICENSE
pykeybasebot-0.2.1.dist-info/WHEEL
pykeybasebot-0.2.1.dist-info/METADATA
pykeybasebot-0.2.1.dist-info/RECORD
