Metadata-Version: 2.1
Name: pykeybasebot
Version: 0.2.1
Summary: Officially supported Keybase python bot client library
Home-page: https://github.com/keybase/pykeybasebot
License: BSD-3-Clause
Author: Keybase Engineering Team
Author-email: alex@keyba.se
Requires-Python: >=3.7,<4.0
Classifier: Framework :: Robot Framework :: Library
Classifier: Framework :: Robot Framework :: Tool
Classifier: License :: OSI Approved :: BSD License
Classifier: Programming Language :: Python :: 3
Classifier: Programming Language :: Python :: 3 :: Only
Classifier: Programming Language :: Python :: 3.7
Requires-Dist: dataclasses-json (>=0.3.2,<0.4.0)
Requires-Dist: typing-extensions (>=3.7,<4.0)
